{
  "version": "0.4.30",
  "flags": {},
  "shapes": [
    {
      "label": "pencil",
      "text": "",
      "points": [
        [
          405.0,
          270.0
        ],
        [
          405.0,
          272.0
        ],
        [
          404.0,
          273.0
        ],
        [
          404.0,
          281.0
        ],
        [
          405.0,
          282.0
        ],
        [
          405.0,
          293.0
        ],
        [
          406.0,
          294.0
        ],
        [
          406.0,
          296.0
        ],
        [
          407.0,
          297.0
        ],
        [
          408.0,
          300.0
        ],
        [
          415.0,
          307.0
        ],
        [
          416.0,
          307.0
        ],
        [
          418.0,
          309.0
        ],
        [
          419.0,
          309.0
        ],
        [
          421.0,
          311.0
        ],
        [
          421.0,
          312.0
        ],
        [
          422.0,
          312.0
        ],
        [
          424.0,
          314.0
        ],
        [
          425.0,
          314.0
        ],
        [
          427.0,
          316.0
        ],
        [
          428.0,
          316.0
        ],
        [
          433.0,
          320.0
        ],
        [
          436.0,
          321.0
        ],
        [
          445.0,
          328.0
        ],
        [
          447.0,
          328.0
        ],
        [
          448.0,
          329.0
        ],
        [
          449.0,
          329.0
        ],
        [
          451.0,
          331.0
        ],
        [
          452.0,
          331.0
        ],
        [
          457.0,
          334.0
        ],
        [
          459.0,
          334.0
        ],
        [
          461.0,
          336.0
        ],
        [
          463.0,
          336.0
        ],
        [
          464.0,
          337.0
        ],
        [
          466.0,
          337.0
        ],
        [
          467.0,
          338.0
        ],
        [
          469.0,
          338.0
        ],
        [
          472.0,
          340.0
        ],
        [
          474.0,
          340.0
        ],
        [
          475.0,
          341.0
        ],
        [
          476.0,
          341.0
        ],
        [
          477.0,
          342.0
        ],
        [
          479.0,
          342.0
        ],
        [
          480.0,
          343.0
        ],
        [
          483.0,
          343.0
        ],
        [
          484.0,
          344.0
        ],
        [
          486.0,
          344.0
        ],
        [
          487.0,
          345.0
        ],
        [
          488.0,
          345.0
        ],
        [
          489.0,
          346.0
        ],
        [
          491.0,
          346.0
        ],
        [
          492.0,
          347.0
        ],
        [
          495.0,
          347.0
        ],
        [
          496.0,
          348.0
        ],
        [
          499.0,
          348.0
        ],
        [
          500.0,
          349.0
        ],
        [
          504.0,
          349.0
        ],
        [
          505.0,
          350.0
        ],
        [
          513.0,
          350.0
        ],
        [
          514.0,
          349.0
        ],
        [
          515.0,
          349.0
        ],
        [
          515.0,
          348.0
        ],
        [
          518.0,
          345.0
        ],
        [
          518.0,
          344.0
        ],
        [
          525.0,
          337.0
        ],
        [
          526.0,
          337.0
        ],
        [
          529.0,
          334.0
        ],
        [
          531.0,
          334.0
        ],
        [
          536.0,
          331.0
        ],
        [
          538.0,
          331.0
        ],
        [
          539.0,
          330.0
        ],
        [
          541.0,
          330.0
        ],
        [
          542.0,
          329.0
        ],
        [
          544.0,
          329.0
        ],
        [
          546.0,
          327.0
        ],
        [
          546.0,
          325.0
        ],
        [
          547.0,
          324.0
        ],
        [
          547.0,
          318.0
        ],
        [
          548.0,
          317.0
        ],
        [
          547.0,
          316.0
        ],
        [
          547.0,
          312.0
        ],
        [
          543.0,
          308.0
        ],
        [
          542.0,
          308.0
        ],
        [
          540.0,
          306.0
        ],
        [
          539.0,
          306.0
        ],
        [
          536.0,
          303.0
        ],
        [
          531.0,
          301.0
        ],
        [
          529.0,
          299.0
        ],
        [
          528.0,
          299.0
        ],
        [
          527.0,
          298.0
        ],
        [
          526.0,
          298.0
        ],
        [
          525.0,
          297.0
        ],
        [
          524.0,
          297.0
        ],
        [
          517.0,
          293.0
        ],
        [
          515.0,
          293.0
        ],
        [
          513.0,
          291.0
        ],
        [
          511.0,
          291.0
        ],
        [
          510.0,
          290.0
        ],
        [
          509.0,
          290.0
        ],
        [
          502.0,
          286.0
        ],
        [
          500.0,
          286.0
        ],
        [
          499.0,
          285.0
        ],
        [
          498.0,
          285.0
        ],
        [
          495.0,
          283.0
        ],
        [
          493.0,
          283.0
        ],
        [
          492.0,
          282.0
        ],
        [
          491.0,
          282.0
        ],
        [
          484.0,
          278.0
        ],
        [
          482.0,
          278.0
        ],
        [
          477.0,
          275.0
        ],
        [
          475.0,
          275.0
        ],
        [
          474.0,
          274.0
        ],
        [
          472.0,
          274.0
        ],
        [
          471.0,
          273.0
        ],
        [
          470.0,
          273.0
        ],
        [
          469.0,
          272.0
        ],
        [
          467.0,
          272.0
        ],
        [
          462.0,
          269.0
        ],
        [
          460.0,
          269.0
        ],
        [
          459.0,
          268.0
        ],
        [
          457.0,
          268.0
        ],
        [
          456.0,
          267.0
        ],
        [
          453.0,
          267.0
        ],
        [
          452.0,
          266.0
        ],
        [
          450.0,
          266.0
        ],
        [
          449.0,
          265.0
        ],
        [
          448.0,
          265.0
        ],
        [
          447.0,
          264.0
        ],
        [
          445.0,
          264.0
        ],
        [
          444.0,
          263.0
        ],
        [
          441.0,
          263.0
        ],
        [
          440.0,
          262.0
        ],
        [
          437.0,
          262.0
        ],
        [
          436.0,
          261.0
        ],
        [
          432.0,
          261.0
        ],
        [
          431.0,
          260.0
        ],
        [
          419.0,
          260.0
        ],
        [
          418.0,
          261.0
        ],
        [
          416.0,
          261.0
        ],
        [
          415.0,
          262.0
        ],
        [
          414.0,
          262.0
        ],
        [
          414.0,
          263.0
        ],
        [
          411.0,
          266.0
        ],
        [
          409.0,
          266.0
        ],
        [
          407.0,
          268.0
        ],
        [
          406.0,
          268.0
        ],
        [
          406.0,
          269.0
        ]
      ],
      "group_id": null,
      "shape_type": "polygon",
      "flags": {}
    },
    {
      "label": "tape",
      "text": "",
      "points": [
        [
          546.0,
          329.0
        ],
        [
          545.0,
          330.0
        ],
        [
          543.0,
          330.0
        ],
        [
          542.0,
          331.0
        ],
        [
          539.0,
          331.0
        ],
        [
          538.0,
          332.0
        ],
        [
          537.0,
          332.0
        ],
        [
          536.0,
          333.0
        ],
        [
          535.0,
          333.0
        ],
        [
          534.0,
          334.0
        ],
        [
          533.0,
          334.0
        ],
        [
          532.0,
          335.0
        ],
        [
          531.0,
          335.0
        ],
        [
          530.0,
          336.0
        ],
        [
          529.0,
          336.0
        ],
        [
          528.0,
          337.0
        ],
        [
          527.0,
          337.0
        ],
        [
          517.0,
          347.0
        ],
        [
          517.0,
          348.0
        ],
        [
          516.0,
          349.0
        ],
        [
          516.0,
          350.0
        ],
        [
          514.0,
          352.0
        ],
        [
          514.0,
          359.0
        ],
        [
          512.0,
          361.0
        ],
        [
          512.0,
          362.0
        ],
        [
          511.0,
          363.0
        ],
        [
          511.0,
          366.0
        ],
        [
          510.0,
          367.0
        ],
        [
          510.0,
          373.0
        ],
        [
          511.0,
          374.0
        ],
        [
          511.0,
          375.0
        ],
        [
          512.0,
          376.0
        ],
        [
          512.0,
          377.0
        ],
        [
          516.0,
          381.0
        ],
        [
          516.0,
          382.0
        ],
        [
          517.0,
          383.0
        ],
        [
          517.0,
          385.0
        ],
        [
          518.0,
          386.0
        ],
        [
          518.0,
          387.0
        ],
        [
          520.0,
          389.0
        ],
        [
          520.0,
          390.0
        ],
        [
          522.0,
          392.0
        ],
        [
          522.0,
          393.0
        ],
        [
          523.0,
          394.0
        ],
        [
          523.0,
          395.0
        ],
        [
          524.0,
          396.0
        ],
        [
          524.0,
          397.0
        ],
        [
          525.0,
          398.0
        ],
        [
          525.0,
          399.0
        ],
        [
          526.0,
          400.0
        ],
        [
          527.0,
          400.0
        ],
        [
          529.0,
          402.0
        ],
        [
          529.0,
          403.0
        ],
        [
          530.0,
          404.0
        ],
        [
          531.0,
          404.0
        ],
        [
          532.0,
          405.0
        ],
        [
          533.0,
          405.0
        ],
        [
          535.0,
          407.0
        ],
        [
          536.0,
          407.0
        ],
        [
          537.0,
          408.0
        ],
        [
          538.0,
          408.0
        ],
        [
          539.0,
          409.0
        ],
        [
          541.0,
          409.0
        ],
        [
          542.0,
          410.0
        ],
        [
          544.0,
          410.0
        ],
        [
          545.0,
          411.0
        ],
        [
          550.0,
          411.0
        ],
        [
          551.0,
          412.0
        ],
        [
          556.0,
          412.0
        ],
        [
          557.0,
          411.0
        ],
        [
          561.0,
          411.0
        ],
        [
          562.0,
          410.0
        ],
        [
          564.0,
          410.0
        ],
        [
          565.0,
          409.0
        ],
        [
          566.0,
          409.0
        ],
        [
          567.0,
          408.0
        ],
        [
          568.0,
          408.0
        ],
        [
          569.0,
          407.0
        ],
        [
          570.0,
          407.0
        ],
        [
          571.0,
          406.0
        ],
        [
          572.0,
          406.0
        ],
        [
          574.0,
          404.0
        ],
        [
          575.0,
          404.0
        ],
        [
          576.0,
          403.0
        ],
        [
          577.0,
          403.0
        ],
        [
          578.0,
          402.0
        ],
        [
          579.0,
          402.0
        ],
        [
          582.0,
          399.0
        ],
        [
          582.0,
          398.0
        ],
        [
          587.0,
          393.0
        ],
        [
          587.0,
          392.0
        ],
        [
          589.0,
          390.0
        ],
        [
          589.0,
          389.0
        ],
        [
          590.0,
          388.0
        ],
        [
          590.0,
          387.0
        ],
        [
          591.0,
          386.0
        ],
        [
          591.0,
          385.0
        ],
        [
          592.0,
          384.0
        ],
        [
          592.0,
          382.0
        ],
        [
          593.0,
          381.0
        ],
        [
          593.0,
          378.0
        ],
        [
          594.0,
          377.0
        ],
        [
          594.0,
          366.0
        ],
        [
          593.0,
          365.0
        ],
        [
          593.0,
          362.0
        ],
        [
          592.0,
          361.0
        ],
        [
          592.0,
          360.0
        ],
        [
          591.0,
          359.0
        ],
        [
          591.0,
          358.0
        ],
        [
          590.0,
          357.0
        ],
        [
          590.0,
          356.0
        ],
        [
          589.0,
          355.0
        ],
        [
          589.0,
          354.0
        ],
        [
          588.0,
          353.0
        ],
        [
          588.0,
          352.0
        ],
        [
          587.0,
          351.0
        ],
        [
          587.0,
          350.0
        ],
        [
          582.0,
          345.0
        ],
        [
          581.0,
          345.0
        ],
        [
          579.0,
          343.0
        ],
        [
          578.0,
          343.0
        ],
        [
          575.0,
          340.0
        ],
        [
          574.0,
          340.0
        ],
        [
          571.0,
          337.0
        ],
        [
          570.0,
          337.0
        ],
        [
          567.0,
          334.0
        ],
        [
          566.0,
          334.0
        ],
        [
          565.0,
          333.0
        ],
        [
          564.0,
          333.0
        ],
        [
          563.0,
          332.0
        ],
        [
          562.0,
          332.0
        ],
        [
          561.0,
          331.0
        ],
        [
          559.0,
          331.0
        ],
        [
          558.0,
          330.0
        ],
        [
          548.0,
          330.0
        ],
        [
          547.0,
          329.0
        ]
      ],
      "group_id": null,
      "shape_type": "polygon",
      "flags": {}
    },
    {
      "label": "pack",
      "text": "",
      "points": [
        [
          407.0,
          328.0
        ],
        [
          407.0,
          330.0
        ],
        [
          406.0,
          331.0
        ],
        [
          406.0,
          337.0
        ],
        [
          407.0,
          338.0
        ],
        [
          407.0,
          349.0
        ],
        [
          408.0,
          350.0
        ],
        [
          408.0,
          359.0
        ],
        [
          409.0,
          360.0
        ],
        [
          409.0,
          367.0
        ],
        [
          410.0,
          368.0
        ],
        [
          410.0,
          373.0
        ],
        [
          411.0,
          374.0
        ],
        [
          411.0,
          380.0
        ],
        [
          412.0,
          381.0
        ],
        [
          412.0,
          385.0
        ],
        [
          413.0,
          386.0
        ],
        [
          413.0,
          387.0
        ],
        [
          415.0,
          389.0
        ],
        [
          415.0,
          390.0
        ],
        [
          416.0,
          391.0
        ],
        [
          416.0,
          401.0
        ],
        [
          417.0,
          402.0
        ],
        [
          417.0,
          409.0
        ],
        [
          418.0,
          410.0
        ],
        [
          418.0,
          411.0
        ],
        [
          419.0,
          411.0
        ],
        [
          420.0,
          412.0
        ],
        [
          425.0,
          412.0
        ],
        [
          426.0,
          411.0
        ],
        [
          434.0,
          411.0
        ],
        [
          436.0,
          413.0
        ],
        [
          436.0,
          417.0
        ],
        [
          437.0,
          418.0
        ],
        [
          446.0,
          418.0
        ],
        [
          447.0,
          417.0
        ],
        [
          448.0,
          417.0
        ],
        [
          448.0,
          416.0
        ],
        [
          452.0,
          412.0
        ],
        [
          452.0,
          409.0
        ],
        [
          451.0,
          408.0
        ],
        [
          451.0,
          403.0
        ],
        [
          450.0,
          402.0
        ],
        [
          450.0,
          397.0
        ],
        [
          449.0,
          396.0
        ],
        [
          449.0,
          393.0
        ],
        [
          448.0,
          392.0
        ],
        [
          448.0,
          388.0
        ],
        [
          447.0,
          387.0
        ],
        [
          447.0,
          380.0
        ],
        [
          446.0,
          379.0
        ],
        [
          446.0,
          378.0
        ],
        [
          447.0,
          377.0
        ],
        [
          447.0,
          375.0
        ],
        [
          448.0,
          374.0
        ],
        [
          448.0,
          371.0
        ],
        [
          447.0,
          370.0
        ],
        [
          447.0,
          367.0
        ],
        [
          446.0,
          366.0
        ],
        [
          446.0,
          356.0
        ],
        [
          445.0,
          355.0
        ],
        [
          445.0,
          351.0
        ],
        [
          444.0,
          350.0
        ],
        [
          444.0,
          348.0
        ],
        [
          443.0,
          347.0
        ],
        [
          443.0,
          345.0
        ],
        [
          442.0,
          344.0
        ],
        [
          442.0,
          339.0
        ],
        [
          441.0,
          338.0
        ],
        [
          441.0,
          335.0
        ],
        [
          440.0,
          334.0
        ],
        [
          440.0,
          329.0
        ],
        [
          439.0,
          328.0
        ],
        [
          439.0,
          326.0
        ],
        [
          438.0,
          325.0
        ],
        [
          437.0,
          325.0
        ],
        [
          436.0,
          324.0
        ],
        [
          433.0,
          324.0
        ],
        [
          432.0,
          325.0
        ],
        [
          425.0,
          325.0
        ],
        [
          424.0,
          326.0
        ],
        [
          418.0,
          326.0
        ],
        [
          417.0,
          327.0
        ],
        [
          411.0,
          327.0
        ],
        [
          410.0,
          328.0
        ]
      ],
      "group_id": null,
      "shape_type": "polygon",
      "flags": {}
    },
    {
      "label": "doll",
      "text": "",
      "points": [
        [
          452.0,
          389.0
        ],
        [
          452.0,
          390.0
        ],
        [
          451.0,
          391.0
        ],
        [
          451.0,
          394.0
        ],
        [
          452.0,
          395.0
        ],
        [
          452.0,
          397.0
        ],
        [
          453.0,
          398.0
        ],
        [
          453.0,
          400.0
        ],
        [
          454.0,
          401.0
        ],
        [
          454.0,
          403.0
        ],
        [
          455.0,
          404.0
        ],
        [
          455.0,
          408.0
        ],
        [
          456.0,
          409.0
        ],
        [
          456.0,
          412.0
        ],
        [
          457.0,
          413.0
        ],
        [
          457.0,
          414.0
        ],
        [
          458.0,
          415.0
        ],
        [
          458.0,
          416.0
        ],
        [
          459.0,
          417.0
        ],
        [
          459.0,
          418.0
        ],
        [
          460.0,
          419.0
        ],
        [
          460.0,
          420.0
        ],
        [
          462.0,
          422.0
        ],
        [
          463.0,
          422.0
        ],
        [
          464.0,
          423.0
        ],
        [
          473.0,
          423.0
        ],
        [
          474.0,
          424.0
        ],
        [
          475.0,
          424.0
        ],
        [
          481.0,
          430.0
        ],
        [
          481.0,
          431.0
        ],
        [
          482.0,
          432.0
        ],
        [
          483.0,
          432.0
        ],
        [
          484.0,
          431.0
        ],
        [
          488.0,
          431.0
        ],
        [
          489.0,
          430.0
        ],
        [
          499.0,
          430.0
        ],
        [
          501.0,
          432.0
        ],
        [
          501.0,
          434.0
        ],
        [
          500.0,
          435.0
        ],
        [
          500.0,
          437.0
        ],
        [
          499.0,
          438.0
        ],
        [
          499.0,
          444.0
        ],
        [
          501.0,
          446.0
        ],
        [
          501.0,
          447.0
        ],
        [
          505.0,
          447.0
        ],
        [
          506.0,
          446.0
        ],
        [
          507.0,
          446.0
        ],
        [
          509.0,
          444.0
        ],
        [
          509.0,
          443.0
        ],
        [
          511.0,
          441.0
        ],
        [
          512.0,
          441.0
        ],
        [
          513.0,
          440.0
        ],
        [
          517.0,
          440.0
        ],
        [
          520.0,
          443.0
        ],
        [
          521.0,
          443.0
        ],
        [
          522.0,
          444.0
        ],
        [
          525.0,
          444.0
        ],
        [
          526.0,
          445.0
        ],
        [
          527.0,
          445.0
        ],
        [
          529.0,
          443.0
        ],
        [
          529.0,
          442.0
        ],
        [
          530.0,
          441.0
        ],
        [
          530.0,
          438.0
        ],
        [
          532.0,
          436.0
        ],
        [
          532.0,
          435.0
        ],
        [
          534.0,
          433.0
        ],
        [
          534.0,
          432.0
        ],
        [
          538.0,
          428.0
        ],
        [
          538.0,
          427.0
        ],
        [
          539.0,
          426.0
        ],
        [
          538.0,
          425.0
        ],
        [
          538.0,
          423.0
        ],
        [
          535.0,
          420.0
        ],
        [
          534.0,
          420.0
        ],
        [
          532.0,
          418.0
        ],
        [
          529.0,
          418.0
        ],
        [
          527.0,
          416.0
        ],
        [
          527.0,
          411.0
        ],
        [
          526.0,
          410.0
        ],
        [
          526.0,
          408.0
        ],
        [
          525.0,
          407.0
        ],
        [
          525.0,
          406.0
        ],
        [
          522.0,
          403.0
        ],
        [
          520.0,
          403.0
        ],
        [
          518.0,
          405.0
        ],
        [
          517.0,
          405.0
        ],
        [
          516.0,
          406.0
        ],
        [
          515.0,
          406.0
        ],
        [
          512.0,
          408.0
        ],
        [
          510.0,
          405.0
        ],
        [
          510.0,
          399.0
        ],
        [
          509.0,
          398.0
        ],
        [
          509.0,
          396.0
        ],
        [
          507.0,
          394.0
        ],
        [
          507.0,
          393.0
        ],
        [
          506.0,
          392.0
        ],
        [
          506.0,
          391.0
        ],
        [
          505.0,
          391.0
        ],
        [
          501.0,
          387.0
        ],
        [
          500.0,
          387.0
        ],
        [
          497.0,
          385.0
        ],
        [
          495.0,
          385.0
        ],
        [
          492.0,
          383.0
        ],
        [
          476.0,
          383.0
        ],
        [
          475.0,
          384.0
        ],
        [
          471.0,
          384.0
        ],
        [
          470.0,
          385.0
        ],
        [
          469.0,
          385.0
        ],
        [
          466.0,
          387.0
        ],
        [
          465.0,
          386.0
        ],
        [
          463.0,
          386.0
        ],
        [
          461.0,
          384.0
        ],
        [
          457.0,
          384.0
        ]
      ],
      "group_id": null,
      "shape_type": "polygon",
      "flags": {}
    }
  ],
  "imagePath": "pc1_mixed_0142.jpg",
  "imageData": null,
  "imageHeight": 720,
  "imageWidth": 1280
}