{
  "version": "0.4.30",
  "flags": {},
  "shapes": [
    {
      "label": "pack",
      "text": "",
      "points": [
        [
          721.0,
          559.0
        ],
        [
          718.0,
          562.0
        ],
        [
          718.0,
          570.0
        ],
        [
          719.0,
          571.0
        ],
        [
          719.0,
          572.0
        ],
        [
          718.0,
          573.0
        ],
        [
          718.0,
          574.0
        ],
        [
          717.0,
          575.0
        ],
        [
          716.0,
          575.0
        ],
        [
          712.0,
          579.0
        ],
        [
          712.0,
          580.0
        ],
        [
          711.0,
          581.0
        ],
        [
          711.0,
          584.0
        ],
        [
          710.0,
          585.0
        ],
        [
          710.0,
          594.0
        ],
        [
          711.0,
          595.0
        ],
        [
          711.0,
          606.0
        ],
        [
          712.0,
          607.0
        ],
        [
          712.0,
          617.0
        ],
        [
          713.0,
          618.0
        ],
        [
          713.0,
          630.0
        ],
        [
          712.0,
          631.0
        ],
        [
          712.0,
          648.0
        ],
        [
          713.0,
          649.0
        ],
        [
          713.0,
          665.0
        ],
        [
          714.0,
          666.0
        ],
        [
          714.0,
          684.0
        ],
        [
          715.0,
          685.0
        ],
        [
          715.0,
          694.0
        ],
        [
          716.0,
          695.0
        ],
        [
          716.0,
          706.0
        ],
        [
          717.0,
          707.0
        ],
        [
          717.0,
          709.0
        ],
        [
          723.0,
          715.0
        ],
        [
          724.0,
          715.0
        ],
        [
          726.0,
          718.0
        ],
        [
          727.0,
          718.0
        ],
        [
          728.0,
          719.0
        ],
        [
          746.0,
          719.0
        ],
        [
          747.0,
          718.0
        ],
        [
          749.0,
          718.0
        ],
        [
          750.0,
          717.0
        ],
        [
          752.0,
          717.0
        ],
        [
          753.0,
          716.0
        ],
        [
          754.0,
          717.0
        ],
        [
          760.0,
          717.0
        ],
        [
          761.0,
          718.0
        ],
        [
          764.0,
          718.0
        ],
        [
          765.0,
          717.0
        ],
        [
          781.0,
          717.0
        ],
        [
          781.0,
          704.0
        ],
        [
          780.0,
          703.0
        ],
        [
          780.0,
          687.0
        ],
        [
          781.0,
          686.0
        ],
        [
          781.0,
          653.0
        ],
        [
          780.0,
          652.0
        ],
        [
          780.0,
          641.0
        ],
        [
          779.0,
          640.0
        ],
        [
          779.0,
          630.0
        ],
        [
          778.0,
          629.0
        ],
        [
          778.0,
          621.0
        ],
        [
          777.0,
          620.0
        ],
        [
          777.0,
          606.0
        ],
        [
          776.0,
          605.0
        ],
        [
          776.0,
          598.0
        ],
        [
          775.0,
          597.0
        ],
        [
          775.0,
          584.0
        ],
        [
          774.0,
          583.0
        ],
        [
          774.0,
          579.0
        ],
        [
          773.0,
          578.0
        ],
        [
          773.0,
          577.0
        ],
        [
          769.0,
          573.0
        ],
        [
          768.0,
          573.0
        ],
        [
          767.0,
          572.0
        ],
        [
          763.0,
          572.0
        ],
        [
          762.0,
          571.0
        ],
        [
          761.0,
          571.0
        ],
        [
          760.0,
          572.0
        ],
        [
          755.0,
          572.0
        ],
        [
          754.0,
          571.0
        ],
        [
          752.0,
          571.0
        ],
        [
          750.0,
          569.0
        ],
        [
          750.0,
          563.0
        ],
        [
          749.0,
          562.0
        ],
        [
          749.0,
          559.0
        ],
        [
          747.0,
          557.0
        ],
        [
          739.0,
          557.0
        ],
        [
          738.0,
          558.0
        ],
        [
          724.0,
          558.0
        ],
        [
          723.0,
          559.0
        ]
      ],
      "group_id": null,
      "shape_type": "polygon",
      "flags": {}
    }
  ],
  "imagePath": "pc1_carton_0032.jpg",
  "imageData": null,
  "imageHeight": 720,
  "imageWidth": 1280
}